odoo/addons/shopfloor_reception/README.rst
odoo/addons/shopfloor_reception/__init__.py
odoo/addons/shopfloor_reception/__manifest__.py
odoo/addons/shopfloor_reception/hooks.py
odoo/addons/shopfloor_reception/actions/__init__.py
odoo/addons/shopfloor_reception/actions/messages.py
odoo/addons/shopfloor_reception/data/shopfloor_scenario_data.xml
odoo/addons/shopfloor_reception/demo/shopfloor_menu_demo.xml
odoo/addons/shopfloor_reception/demo/stock_picking_type_demo.xml
odoo/addons/shopfloor_reception/docs/reception_sequence_graph.mermaid
odoo/addons/shopfloor_reception/docs/reception_sequence_graph.png
odoo/addons/shopfloor_reception/i18n/it.po
odoo/addons/shopfloor_reception/i18n/shopfloor_reception.pot
odoo/addons/shopfloor_reception/models/__init__.py
odoo/addons/shopfloor_reception/models/shopfloor_menu.py
odoo/addons/shopfloor_reception/readme/CONTRIBUTORS.md
odoo/addons/shopfloor_reception/readme/DESCRIPTION.md
odoo/addons/shopfloor_reception/readme/ROADMAP.md
odoo/addons/shopfloor_reception/services/__init__.py
odoo/addons/shopfloor_reception/services/reception.py
odoo/addons/shopfloor_reception/static/description/icon.png
odoo/addons/shopfloor_reception/static/description/index.html
odoo/addons/shopfloor_reception/tests/__init__.py
odoo/addons/shopfloor_reception/tests/common.py
odoo/addons/shopfloor_reception/tests/reception_return_common.py
odoo/addons/shopfloor_reception/tests/test_assign_package_type.py
odoo/addons/shopfloor_reception/tests/test_change_package_type.py
odoo/addons/shopfloor_reception/tests/test_manual_selection.py
odoo/addons/shopfloor_reception/tests/test_reception_done.py
odoo/addons/shopfloor_reception/tests/test_recover.py
odoo/addons/shopfloor_reception/tests/test_return_reception_done.py
odoo/addons/shopfloor_reception/tests/test_return_scan_document.py
odoo/addons/shopfloor_reception/tests/test_return_scan_line.py
odoo/addons/shopfloor_reception/tests/test_return_set_quantity.py
odoo_addon_shopfloor_reception-18.0.1.6.2.dist-info/METADATA
odoo_addon_shopfloor_reception-18.0.1.6.2.dist-info/WHEEL
odoo_addon_shopfloor_reception-18.0.1.6.2.dist-info/top_level.txt
odoo_addon_shopfloor_reception-18.0.1.6.2.dist-info/RECORD
